README.md
setup.cfg
setup.py
date_helper_pkg/__init__.py
date_helper_pkg/date_helper.py
pinkfloyd92.egg-info/PKG-INFO
pinkfloyd92.egg-info/SOURCES.txt
pinkfloyd92.egg-info/dependency_links.txt
pinkfloyd92.egg-info/requires.txt
pinkfloyd92.egg-info/top_level.txt